call_flow/__init__.py
call_flow/tools/__init__.py
call_flow/tools/call_flow_tool.py
call_flow/tools/utils.py
call_flow/yamls/call_flow_tool.yaml
tests/__init__.py
tests/test_call_flow_tool.py
placeIntelligence_flow-0.0.2.dist-info/METADATA
placeIntelligence_flow-0.0.2.dist-info/WHEEL
placeIntelligence_flow-0.0.2.dist-info/entry_points.txt
placeIntelligence_flow-0.0.2.dist-info/top_level.txt
placeIntelligence_flow-0.0.2.dist-info/RECORD
