Metadata-Version: 2.1
Name: placeIntelligence_flow
Version: 0.0.2
Summary: Import another flow in prompt flow
